discogs_record_shelf-1.0.3.dist-info/licenses/LICENSE
record_shelf/__init__.py
record_shelf/cli.py
record_shelf/config.py
record_shelf/py.typed
record_shelf/report_generator.py
record_shelf/utils.py
discogs_record_shelf-1.0.3.dist-info/METADATA
discogs_record_shelf-1.0.3.dist-info/WHEEL
discogs_record_shelf-1.0.3.dist-info/entry_points.txt
discogs_record_shelf-1.0.3.dist-info/top_level.txt
discogs_record_shelf-1.0.3.dist-info/RECORD
